zoneplanningteam/__init__.py
zoneplanningteam/zoneplanning.py
zoneplanningteam-0.0.3.dist-info/METADATA
zoneplanningteam-0.0.3.dist-info/WHEEL
zoneplanningteam-0.0.3.dist-info/top_level.txt
zoneplanningteam-0.0.3.dist-info/RECORD
