Metadata-Version: 2.1
Name: zoneplanningteam
Version: 0.0.3
Summary: First zone planning team package
Home-page: UNKNOWN
Author: Pablo Galaz Cares
Author-email: <pablo.galaz.c@ug.uchile.cl>
License: UNKNOWN
Keywords: python,first package
Platform: UNKNOWN
Classifier: Development Status :: 3 - Alpha
Classifier: Intended Audience :: Education
Classifier: Programming Language :: Python :: 2
Classifier: Programming Language :: Python :: 3
Classifier: Operating System :: MacOS :: MacOS X
Classifier: Operating System :: Microsoft :: Windows
